{"hippokrates-larljunge_2026_sk-kurs-aldre-sjuka.md":"DWpXBKWM","hippokrates-larljunge_hippokrates-larljunge.md":"Bjim9AU7","hippokrates-larljunge_index.md":"kon2tIwN","index.md":"CvTQF1Z_","internmedicin_erysipelas.md":"DfiwX1RS","internmedicin_index.md":"B_VDpV7V","kardiologi_index.md":"Beldu2vs","kardiologi_stemi.md":"C-JOrz5w","kirurgi_index.md":"DkWm5p9O","kontakt.md":"ClW_fxz6","laboratorieanalyser_blodstatus.md":"M45-meh_","laboratorieanalyser_index.md":"Cw3atvkj","medicinsk-statistik_index.md":"DxJzQm7q","medicinsk-statistik_pretest-probability-ptp.md":"ClawUD-I","medicinsk-statistik_sensitivitet-och-specificitet.md":"DeNh7hI7","sarvard_antibiotika.md":"CyZzTtdm","sarvard_index.md":"CUApvmXZ","sarvard_listor-och-patientinfo.md":"BUZDZH1M","taligenkanning_index.md":"DbKJopuB","taligenkanning_lathund-akuten.md":"C-GZguxy","internmedicin_venos-tromboembolism-vte.md":"wAUGJ1z6","medicinsk-statistik_likelyhood-ratio-lr.md":"C1NNv0Xt","om.md":"CKEnNsEn","kirurgi_appendicit.md":"CpCBfnhI","medicinsk-statistik_fagans-nomogram.md":"PCaZYwjO","medicinsk-statistik_positivt-prediktivt-varde-ppv.md":"C43vHLSS","sarvard_hudbiologi.md":"DXaMX2EY","taligenkanning_how-to.md":"CI5maoeg","sarvard_handlaggning.md":"T4EKB3Wv"}
