{"hippokrates-lärljunge_2025_2025-09-14.md":"DnJ0bm8o","hippokrates-lärljunge_hippokrates-lärljunge.md":"wtH-56kI","index.md":"D-O6Ip_N","internmedicin_erysipelas.md":"eHPgrEOi","kardiologi_stemi.md":"DLnnnsP0","kontakt.md":"BcYRPicf","medicinsk-statistik_1. sensitivitet-och-specificitet.md":"Br6Z-79h","medicinsk-statistik_3. pretest-probability-(ptp).md":"Bk5dXTBv","prislista-mse_bilddiagnostik.md":"CUI9z85t","prislista-mse_laboratorieanalyser.md":"CToYnHa9","taligenkänning_lathund-akuten.md":"BO7z-twm","internmedicin_venös-tromboembolism-(vte).md":"DSfcYFuD","medicinsk-statistik_4. likelyhood-ratio-(lr).md":"CWy5Z7Fj","om.md":"lZ9O17Zj","kirurgi_appendicit.md":"BhTlQFTy","medicinsk-statistik_2. positivt-prediktivt-värde-(ppv).md":"DwMFDs-8","medicinsk-statistik_5. fagans-nomogram.md":"BgRoapGa","taligenkänning_how-to.md":"C54gzvbl","sårvård_sårvård.md":"BuP-HSbx"}
